region_grower/__init__.py
region_grower/atlas_helper.py
region_grower/cli.py
region_grower/context.py
region_grower/generate.py
region_grower/modify.py
region_grower/morph_io.py
region_grower/synthesize_morphologies.py
region_grower/utils.py
region_grower/version.py
region_grower/data/pc_in_types.yaml
region_grower/schemas/distributions.json
region_grower/schemas/parameters.json
region_grower-1.6.0.dist-info/AUTHORS.md
region_grower-1.6.0.dist-info/LICENSE.txt
region_grower-1.6.0.dist-info/METADATA
region_grower-1.6.0.dist-info/WHEEL
region_grower-1.6.0.dist-info/entry_points.txt
region_grower-1.6.0.dist-info/top_level.txt
region_grower-1.6.0.dist-info/RECORD
