Metadata-Version: 2.1
Name: region-grower
Version: 1.6.0
Summary: Synthesize cells in a given spatial context.
Home-page: https://region-grower.readthedocs.io
Author: Blue Brain Project, EPFL
License: Apache License 2.0
Project-URL: Tracker, https://github.com/BlueBrain/region-grower/issues
Project-URL: Source, https://github.com/BlueBrain/region-grower
Classifier: Development Status :: 4 - Beta
Classifier: Intended Audience :: Education
Classifier: Intended Audience :: Science/Research
Classifier: Programming Language :: Python
Classifier: Programming Language :: Python :: 3
Classifier: Programming Language :: Python :: 3.9
Classifier: Programming Language :: Python :: 3.10
Classifier: Programming Language :: Python :: 3.11
Classifier: Programming Language :: Python :: 3.12
Classifier: Topic :: Scientific/Engineering :: Bio-Informatics
Requires-Python: >=3.9
License-File: LICENSE.txt
License-File: AUTHORS.md
Requires-Dist: attrs>=19.3.0
Requires-Dist: click>=8.0
Requires-Dist: dask[dataframe,distributed]>=2023.3.2
Requires-Dist: diameter-synthesis<1,>=0.5.4
Requires-Dist: morphio<4,>=3.3.6
Requires-Dist: morph-tool[nrn]<3,>=2.11
Requires-Dist: neuroc<1,>=0.3
Requires-Dist: neurom<4,>=3.2
Requires-Dist: neurots<4,>=3.6
Requires-Dist: numpy>=1.26
Requires-Dist: pandas>=2.1
Requires-Dist: tqdm>=4.60
Requires-Dist: voxcell<4,>=3.1.5
Requires-Dist: pynrrd>=0.4.0
Requires-Dist: trimesh>=3.23
Requires-Dist: rtree>=1.0.1
Provides-Extra: docs
Requires-Dist: docutils<0.21; extra == "docs"
Requires-Dist: m2r2; extra == "docs"
Requires-Dist: sphinx; extra == "docs"
Requires-Dist: sphinx-bluebrain-theme; extra == "docs"
Requires-Dist: sphinx-jsonschema; extra == "docs"
Requires-Dist: sphinx-click; extra == "docs"
Provides-Extra: mpi
Requires-Dist: dask_mpi>=2022.4; extra == "mpi"
Requires-Dist: mpi4py>=3.1.1; extra == "mpi"
Provides-Extra: test
Requires-Dist: brainbuilder>=0.20.1; extra == "test"
Requires-Dist: dictdiffer>=0.9; extra == "test"
Requires-Dist: pytest>=6.2.5; extra == "test"
Requires-Dist: pytest-click>=1; extra == "test"
Requires-Dist: pytest-console-scripts>=1.3; extra == "test"
Requires-Dist: pytest-cov>=3; extra == "test"
Requires-Dist: pytest-html>=2; extra == "test"
Requires-Dist: pytest-mock>=3.5; extra == "test"
Requires-Dist: pytest-xdist>=3.0.2; extra == "test"
Requires-Dist: neurocollage>=0.3.6; extra == "test"
Requires-Dist: scikit-image>=0.19; extra == "test"
